LICENSE
MANIFEST.in
manage.py
readme.md
requirements.in
requirements.txt
setup.cfg
setup.py
core/__init__.py
core/settings.py
core/urls.py
core/wsgi.py
datafreezer/__init__.py
datafreezer/admin.py
datafreezer/apps.py
datafreezer/forms.py
datafreezer/helpers.py
datafreezer/models.py
datafreezer/seed_db.py
datafreezer/signals.py
datafreezer/storages.py
datafreezer/tests.py
datafreezer/urls.py
datafreezer/validators.py
datafreezer/views.py
datafreezer/views_compat.py
datafreezer/management/__init__.py
datafreezer/management/commands/__init__.py
datafreezer/migrations/0001_initial.py
datafreezer/migrations/0002_dataset_has_headers.py
datafreezer/migrations/0003_auto_20160727_1640.py
datafreezer/migrations/0004_datadictionaryfield_columnindex.py
datafreezer/migrations/0005_auto_20160810_1607.py
datafreezer/migrations/0006_auto_20160817_1053.py
datafreezer/migrations/0007_auto_20160817_1133.py
datafreezer/migrations/0008_auto_20160818_1431.py
datafreezer/migrations/0009_auto_20160818_1549.py
datafreezer/migrations/0010_auto_20160818_1554.py
datafreezer/migrations/0011_auto_20160818_1600.py
datafreezer/migrations/0012_auto_20160818_1612.py
datafreezer/migrations/0013_dataset_source.py
datafreezer/migrations/0014_dataset_source_slug.py
datafreezer/migrations/0015_auto_20160824_1452.py
datafreezer/migrations/0016_auto_20160829_1428.py
datafreezer/migrations/__init__.py
datafreezer/static/.DS_Store
datafreezer/static/datafreezer/.DS_Store
datafreezer/static/datafreezer/css/styles.css
datafreezer/static/datafreezer/img/.DS_Store
datafreezer/static/datafreezer/img/datafreezer_icon_favicon.png
datafreezer/static/datafreezer/img/datafreezer_icon_touch.png
datafreezer/static/datafreezer/img/datafreezer_logo.svg
datafreezer/static/datafreezer/img/datafreezer_logo_dark.svg
datafreezer/static/datafreezer/img/dmn_masthead.svg
datafreezer/static/datafreezer/js/script.js
datafreezer/templates/datafreezer/author_detail.html
datafreezer/templates/datafreezer/base.html
django_datafreezer.egg-info/PKG-INFO
django_datafreezer.egg-info/SOURCES.txt
django_datafreezer.egg-info/dependency_links.txt
django_datafreezer.egg-info/not-zip-safe
django_datafreezer.egg-info/requires.txt
django_datafreezer.egg-info/top_level.txt