Metadata-Version: 1.1
Name: django-datafreezer
Version: 0.2.0
Summary: Data storage Django web application.
Home-page: https://github.com/dallasmorningnews/django-datafreezer
Author: Tyler Allyn Davis, The Dallas Morning News
Author-email: tallyndavis@comcast.net
License: MIT
Download-URL: https://github.com/dallasmorningnews/django-datafreezer/tarball/0.2.0
Keywords: django,csv,data,storage,journalism,javascript
Platform: UNKNOWN
Classifier: Development Status :: 5 - Production/Stable
Classifier: Environment :: Web Environment
Classifier: Framework :: Django
Classifier: Intended Audience :: Developers
Classifier: License :: OSI Approved :: MIT License
Classifier: Operating System :: OS Independent
Classifier: Programming Language :: Python
Classifier: Programming Language :: Python :: 2
Classifier: Programming Language :: Python :: 2.6
Classifier: Programming Language :: Python :: 2.7
